hubtel_ai/cli/__init__.py
hubtel_ai/cli/cli.py
hubtel_ai/cli/commands/__init__.py
hubtel_ai/cli/commands/init.py
hubtel_ai/cli/commands/main.py
hubtel_ai/cli/commands/validate.py
hubtel_ai/cli/commands/version.py
hubtel_ai/cli/cookiecutter/cookiecutter.json
hubtel_ai/cli/cookiecutter/{{cookiecutter.integration_slug}}/.gitignore
hubtel_ai/cli/cookiecutter/{{cookiecutter.integration_slug}}/CHANGELOG.md
hubtel_ai/cli/cookiecutter/{{cookiecutter.integration_slug}}/README.md
hubtel_ai/cli/cookiecutter/{{cookiecutter.integration_slug}}/changelog/.gitignore
hubtel_ai/cli/cookiecutter/{{cookiecutter.integration_slug}}/functions/predictor/Dockerfile
hubtel_ai/cli/cookiecutter/{{cookiecutter.integration_slug}}/functions/predictor/requirements.txt
hubtel_ai/cli/cookiecutter/{{cookiecutter.integration_slug}}/functions/predictor/src/__init__.py
hubtel_ai/cli/cookiecutter/{{cookiecutter.integration_slug}}/functions/predictor/src/app.py
hubtel_ai/cli/cookiecutter/{{cookiecutter.integration_slug}}/functions/processor/Dockerfile
hubtel_ai/cli/cookiecutter/{{cookiecutter.integration_slug}}/functions/processor/requirements.txt
hubtel_ai/cli/cookiecutter/{{cookiecutter.integration_slug}}/functions/processor/src/__init__.py
hubtel_ai/cli/cookiecutter/{{cookiecutter.integration_slug}}/functions/processor/src/app.py
hubtel_ai/cli/cookiecutter/{{cookiecutter.integration_slug}}/pyproject.toml
hubtel_ai/cli/cookiecutter/{{cookiecutter.integration_slug}}/template.yaml
hubtel_ai/cli/cookiecutter/{{cookiecutter.integration_slug}}/test/test_prediction.json
hubtel_ai/cli/utils.py
hubtel_ai/cli/version.py
hubtel_ai-0.1.0.dist-info/METADATA
hubtel_ai-0.1.0.dist-info/WHEEL
hubtel_ai-0.1.0.dist-info/entry_points.txt
hubtel_ai-0.1.0.dist-info/RECORD
