Metadata-Version: 2.1
Name: hubtel-ai
Version: 0.1.0
Summary: Hubtel AI is a CLI tool for managing your Hubtel AI deployment projects.
Author: Ing Michael Kofi Armah
Author-email: mikeyarmah@gmail.com
Requires-Python: >=3.11,<4.0
Classifier: Programming Language :: Python :: 3
Classifier: Programming Language :: Python :: 3.11
Classifier: Programming Language :: Python :: 3.12
Requires-Dist: cookiecutter (>=2.5.0,<3.0.0)
Requires-Dist: rich (>=13.7.0,<14.0.0)
Requires-Dist: tomli (>=2.0.1,<3.0.0)
